stolid/__init__.py
stolid/_ast_inspection.py
stolid/_constants.py
stolid/checker.py
stolid/tests/__init__.py
stolid/tests/code_parser.py
stolid/tests/test_edge_cases.py
stolid/tests/test_init.py
stolid/tests/test_sld1xx.py
stolid/tests/test_sld2xx.py
stolid/tests/test_sld3xx.py
stolid/tests/test_sld4xx.py
stolid/tests/test_sld5xx.py
stolid/tests/test_sld6xx.py
stolid/tests/test_sld7xx.py
stolid-2026.1.24.80598.dist-info/METADATA
stolid-2026.1.24.80598.dist-info/WHEEL
stolid-2026.1.24.80598.dist-info/entry_points.txt
stolid-2026.1.24.80598.dist-info/top_level.txt
stolid-2026.1.24.80598.dist-info/RECORD
