Metadata-Version: 2.4
Name: stolid
Version: 2026.1.24.80598
Summary: Linter enforcing the conventions of the Python standard template
Author-email: Moshe Zadka <moshez@zadka.club>
License: Permission is hereby granted, free of charge, to any person obtaining a
Project-URL: Homepage, https://github.com/moshez/stolid
Provides-Extra: tests
Requires-Dist: virtue; extra == "tests"
Requires-Dist: pyhamcrest; extra == "tests"
Requires-Dist: coverage; extra == "tests"
Provides-Extra: mypy
Requires-Dist: mypy; extra == "mypy"
Provides-Extra: lint
Requires-Dist: flake8; extra == "lint"
Requires-Dist: black; extra == "lint"
Provides-Extra: docs
Requires-Dist: sphinx; extra == "docs"
